meditation_video_generator/__init__.py
meditation_video_generator/ambient_files_urls.txt
meditation_video_generator/meditation_video_generator.py
meditation_video_generator/mp3_merger.py
meditation_video_generator/mp3_mixer.py
meditation_video_generator/visual_prompts_list.py
meditation_video_generator_openai-1.1.4.dist-info/METADATA
meditation_video_generator_openai-1.1.4.dist-info/WHEEL
meditation_video_generator_openai-1.1.4.dist-info/top_level.txt
meditation_video_generator_openai-1.1.4.dist-info/RECORD
