Metadata-Version: 2.1
Name: meditation-video-generator-openai
Version: 1.1.4
Summary: A tool to create guided meditations (like those found on YouTube) using OpenAI and ElevenLabs.
Author: Alexis Kirke
Author-email: alexiskirke2@gmail.com
Classifier: Programming Language :: Python :: 3
Classifier: License :: OSI Approved :: MIT License
Classifier: Operating System :: OS Independent
Requires-Python: >=3.6
Requires-Dist: pedalboard
Requires-Dist: pydub
Requires-Dist: openai
Requires-Dist: requests
Requires-Dist: moviepy
Requires-Dist: pillow
Requires-Dist: elevenlabs
